prpolish/__init__.py
prpolish/cli.py
prpolish/clipboard.py
prpolish/git_utils.py
prpolish/pr_description.py
prpolish/vibe_check.py
prpolish-0.3.2.dist-info/licenses/LICENSE
prpolish-0.3.2.dist-info/METADATA
prpolish-0.3.2.dist-info/WHEEL
prpolish-0.3.2.dist-info/entry_points.txt
prpolish-0.3.2.dist-info/top_level.txt
prpolish-0.3.2.dist-info/RECORD
