Metadata-Version: 2.4
Name: prpolish
Version: 0.3.2
Summary: A CLI tool to generate PR titles and descriptions for Git repositories
Home-page: https://github.com/yashg4509/prpolish
Author: Yash Gupta
Author-email: ysgupta@wisc.edu
Classifier: Programming Language :: Python :: 3
Classifier: License :: OSI Approved :: MIT License
Classifier: Operating System :: OS Independent
Requires-Python: >=3.7
License-File: LICENSE
Requires-Dist: click
Requires-Dist: GitPython
Requires-Dist: pyperclip
Dynamic: author
Dynamic: author-email
Dynamic: classifier
Dynamic: description
Dynamic: description-content-type
Dynamic: home-page
Dynamic: license-file
Dynamic: requires-dist
Dynamic: requires-python
Dynamic: summary
